m3_registry-2.4.1.dist-info/licenses/LICENSE
registry/__init__.py
registry/core.py
registry/cumulative.py
registry/data_registry.py
registry/exceptions.py
registry/info_reg.py
registry/info_registry.py
registry/models.py
m3_registry-2.4.1.dist-info/METADATA
m3_registry-2.4.1.dist-info/WHEEL
m3_registry-2.4.1.dist-info/top_level.txt
m3_registry-2.4.1.dist-info/RECORD
